LICENSE
MANIFEST.in
README.md
setup.cfg
setup.py
ringo_file/__init__.py
ringo_file/files.json
ringo_file/files.xml
ringo_file/model.py
ringo_file/views.py
ringo_file.egg-info/PKG-INFO
ringo_file.egg-info/SOURCES.txt
ringo_file.egg-info/dependency_links.txt
ringo_file.egg-info/entry_points.txt
ringo_file.egg-info/not-zip-safe
ringo_file.egg-info/requires.txt
ringo_file.egg-info/top_level.txt
ringo_file/locale/ringo_file.pot