Metadata-Version: 1.0
Name: ringo-file
Version: 1.0
Summary: Extension for file attachments in the ringo webframework
Home-page: https://github.com/ringo-framework/ringo_file
Author: Torsten Irländer
Author-email: torsten.irlaender@googlemail.com
License: GPL
Keywords: ringo pyramid extension
Platform: UNKNOWN
